a2a/__init__.py
a2a/_base.py
a2a/py.typed
a2a/types.py
a2a/auth/__init__.py
a2a/auth/user.py
a2a/client/__init__.py
a2a/client/base_client.py
a2a/client/card_resolver.py
a2a/client/client.py
a2a/client/client_factory.py
a2a/client/client_task_manager.py
a2a/client/errors.py
a2a/client/helpers.py
a2a/client/legacy.py
a2a/client/legacy_grpc.py
a2a/client/middleware.py
a2a/client/optionals.py
a2a/client/auth/__init__.py
a2a/client/auth/credentials.py
a2a/client/auth/interceptor.py
a2a/client/transports/__init__.py
a2a/client/transports/base.py
a2a/client/transports/grpc.py
a2a/client/transports/jsonrpc.py
a2a/client/transports/rest.py
a2a/extensions/__init__.py
a2a/extensions/common.py
a2a/grpc/__init__.py
a2a/grpc/a2a_pb2.py
a2a/grpc/a2a_pb2.pyi
a2a/grpc/a2a_pb2_grpc.py
a2a/server/__init__.py
a2a/server/context.py
a2a/server/id_generator.py
a2a/server/models.py
a2a/server/agent_execution/__init__.py
a2a/server/agent_execution/agent_executor.py
a2a/server/agent_execution/context.py
a2a/server/agent_execution/request_context_builder.py
a2a/server/agent_execution/simple_request_context_builder.py
a2a/server/apps/__init__.py
a2a/server/apps/jsonrpc/__init__.py
a2a/server/apps/jsonrpc/fastapi_app.py
a2a/server/apps/jsonrpc/jsonrpc_app.py
a2a/server/apps/jsonrpc/starlette_app.py
a2a/server/apps/rest/__init__.py
a2a/server/apps/rest/fastapi_app.py
a2a/server/apps/rest/rest_adapter.py
a2a/server/events/__init__.py
a2a/server/events/event_consumer.py
a2a/server/events/event_queue.py
a2a/server/events/in_memory_queue_manager.py
a2a/server/events/queue_manager.py
a2a/server/request_handlers/__init__.py
a2a/server/request_handlers/default_request_handler.py
a2a/server/request_handlers/grpc_handler.py
a2a/server/request_handlers/jsonrpc_handler.py
a2a/server/request_handlers/request_handler.py
a2a/server/request_handlers/response_helpers.py
a2a/server/request_handlers/rest_handler.py
a2a/server/tasks/__init__.py
a2a/server/tasks/base_push_notification_sender.py
a2a_sdk-0.3.21.dist-info/METADATA
a2a_sdk-0.3.21.dist-info/WHEEL
a2a_sdk-0.3.21.dist-info/licenses/LICENSE
a2a_sdk-0.3.21.dist-info/RECORD
