Metadata-Version: 2.4
Name: a2a-sdk
Version: 0.3.21
Summary: A2A Python SDK
Project-URL: homepage, https://a2a-protocol.org/
Project-URL: repository, https://github.com/a2aproject/a2a-python
Project-URL: changelog, https://github.com/a2aproject/a2a-python/blob/main/CHANGELOG.md
Project-URL: documentation, https://a2a-protocol.org/latest/sdk/python/
Author-email: Google LLC <googleapis-packages@google.com>
License-Expression: Apache-2.0
License-File: LICENSE
Keywords: A2A,A2A Protocol,A2A SDK,Agent 2 Agent,Agent2Agent
Classifier: Intended Audience :: Developers
Classifier: License :: OSI Approved :: Apache Software License
Classifier: Operating System :: OS Independent
Classifier: Programming Language :: Python
Classifier: Programming Language :: Python :: 3
Classifier: Programming Language :: Python :: 3.10
Classifier: Programming Language :: Python :: 3.11
Classifier: Programming Language :: Python :: 3.12
Classifier: Programming Language :: Python :: 3.13
Classifier: Topic :: Software Development :: Libraries :: Python Modules
Requires-Python: >=3.10
Requires-Dist: google-api-core>=1.26.0
Requires-Dist: httpx-sse>=0.4.0
Requires-Dist: httpx>=0.28.1
Requires-Dist: protobuf>=5.29.5
Requires-Dist: pydantic>=2.11.3
Provides-Extra: all
Requires-Dist: cryptography>=43.0.0; extra == 'all'
Requires-Dist: fastapi>=0.115.2; extra == 'all'
Requires-Dist: grpcio-reflection>=1.7.0; extra == 'all'
Requires-Dist: grpcio-tools>=1.60; extra == 'all'
Requires-Dist: grpcio>=1.60; extra == 'all'
Requires-Dist: opentelemetry-api>=1.33.0; extra == 'all'
Requires-Dist: opentelemetry-sdk>=1.33.0; extra == 'all'
Requires-Dist: pyjwt>=2.0.0; extra == 'all'
Requires-Dist: sqlalchemy[aiomysql,asyncio]>=2.0.0; extra == 'all'
Requires-Dist: sqlalchemy[aiosqlite,asyncio]>=2.0.0; extra == 'all'
Requires-Dist: sqlalchemy[asyncio,postgresql-asyncpg]>=2.0.0; extra == 'all'
Requires-Dist: sse-starlette; extra == 'all'
Requires-Dist: starlette; extra == 'all'
Provides-Extra: encryption
Requires-Dist: cryptography>=43.0.0; extra == 'encryption'
Provides-Extra: grpc
Requires-Dist: grpcio-reflection>=1.7.0; extra == 'grpc'
Requires-Dist: grpcio-tools>=1.60; extra == 'grpc'
Requires-Dist: grpcio>=1.60; extra == 'grpc'
Provides-Extra: http-server
Requires-Dist: fastapi>=0.115.2; extra == 'http-server'
Requires-Dist: sse-starlette; extra == 'http-server'
Requires-Dist: starlette; extra == 'http-server'
Provides-Extra: mysql
Requires-Dist: sqlalchemy[aiomysql,asyncio]>=2.0.0; extra == 'mysql'
Provides-Extra: postgresql
Requires-Dist: sqlalchemy[asyncio,postgresql-asyncpg]>=2.0.0; extra == 'postgresql'
Provides-Extra: signing
Requires-Dist: pyjwt>=2.0.0; extra == 'signing'
Provides-Extra: sql
Requires-Dist: sqlalchemy[aiomysql,asyncio]>=2.0.0; extra == 'sql'
Requires-Dist: sqlalchemy[aiosqlite,asyncio]>=2.0.0; extra == 'sql'
Requires-Dist: sqlalchemy[asyncio,postgresql-asyncpg]>=2.0.0; extra == 'sql'
Provides-Extra: sqlite
Requires-Dist: sqlalchemy[aiosqlite,asyncio]>=2.0.0; extra == 'sqlite'
Provides-Extra: telemetry
Requires-Dist: opentelemetry-api>=1.33.0; extra == 'telemetry'
Requires-Dist: opentelemetry-sdk>=1.33.0; extra == 'telemetry'
